Workbook

Sheet Model
A1: Sandisk Corp | V1: Model Info
A2: EDGAR Model (values in $Ms) | V2: Generated: 2026-04-20
B3: Q324 | C3: Q424 | D3: Q125 | E3: Q225 | F3: Q325 | G3: Q425 | H3: Q126 | I3: Q226 | J3: Q326 | K3: Q426 | L3: Q127 | M3: Q227 | N3: Q327 | O3: Q427 | P3: Q128 | Q3: Q228 | R3: Q328 | S3: Q428 | V3: Next Earnings: 2026-04-30
A4: Revenue | B4: 1705 | C4: 1760 | D4: 1883 | E4: 1876 | F4: 1695 | G4: 1901 | H4: 2308 | I4: 3025 | J4: =IF(Drivers!J8<>0,Drivers!J8,F4*(1+0.2918)) -> 4600 | K4: =IF(Drivers!K8<>0,Drivers!K8,G4*(1+0.2896)) -> 4568 | L4: =IF(Drivers!L8<>0,Drivers!L8,H4*(1+0.2835)) -> 4401 | M4: =IF(Drivers!M8<>0,Drivers!M8,I4*(1+0.2739)) -> 4238 | N4: =IF(Drivers!N8<>0,Drivers!N8,J4*(1+0.2613)) -> 3912 | O4: =IF(Drivers!O8<>0,Drivers!O8,K4*(1+0.2461)) -> 3749 | P4: =IF(Drivers!P8<>0,Drivers!P8,L4*(1+0.2288)) -> 5154.8 | Q4: =IF(Drivers!Q8<>0,Drivers!Q8,M4*(1+0.2098)) -> 4964 | R4: =IF(Drivers!R8<>0,Drivers!R8,N4*(1+0.1897)) -> 4582.2 | S4: =IF(Drivers!S8<>0,Drivers!S8,O4*(1+0.1689)) -> 4391.2 | V4: FY End: Unknown
A5: COGS | B5: 1242 | C5: 1124 | D5: 1157 | E5: 1270 | F5: 1313 | G5: 1403 | H5: 1621 | I5: 1484 | J5: =J4*0.34 -> 1564 | K5: =K4*0.36 -> 1644.48 | L5: =L4*0.42 -> 1848.42 | M5: =M4*0.52 -> 2203.76 | N5: =N4*0.6084 -> 2380.0608 | O5: =O4*0.6084 -> 2280.8916 | P5: =P4*0.6084 -> 3136.1803 | Q5: =Q4*0.6084 -> 3020.0976 | R5: =R4*0.6084 -> 2787.8105 | S5: =S4*0.6084 -> 2671.6061
A6: Gross Profit | B6: =B4-B5 -> 463 | C6: =C4-C5 -> 636 | D6: =D4-D5 -> 726 | E6: =E4-E5 -> 606 | F6: =F4-F5 -> 382 | G6: =G4-G5 -> 498 | H6: =H4-H5 -> 687 | I6: =I4-I5 -> 1541 | ... S6: =S4-S5 -> 1719.5939
A7: S&M
A8: R&D | B8: 277 | C8: 298 | D8: 283 | E8: 279 | F8: 285 | G8: 285 | H8: 316 | I8: 327 | J8: =J4*0.125 -> 575 | K8: =K4*0.125 -> 571 | L8: =L4*0.125 -> 550.125 | M8: =M4*0.125 -> 529.75 | N8: =N4*0.125 -> 489 | O8: =O4*0.125 -> 468.625 | P8: =P4*0.125 -> 644.35 | Q8: =Q4*0.125 -> 620.5 | ... S8: =S4*0.125 -> 548.9
A9: G&A | B9: 107 | C9: 117 | D9: 130 | E9: 142 | F9: 139 | G9: 162 | H9: 179 | I9: 139 | J9: =J4*0.063 -> 289.8 | K9: =K4*0.063 -> 287.784 | L9: =L4*0.063 -> 277.263 | M9: =M4*0.063 -> 266.994 | N9: =N4*0.063 -> 246.456 | O9: =O4*0.063 -> 236.187 | P9: =P4*0.063 -> 324.7524 | Q9: =Q4*0.063 -> 312.732 | ... S9: =S4*0.063 -> 276.6456
A10: Operating Expenses | B10: =B7+B8+B9 -> 384 | C10: =C7+C8+C9 -> 415 | D10: =D7+D8+D9 -> 413 | E10: =E7+E8+E9 -> 421 | F10: =F7+F8+F9 -> 424 | G10: =G7+G8+G9 -> 447 | H10: =H7+H8+H9 -> 495 | I10: =I7+I8+I9 -> 466 | ... S10: =S7+S8+S9 -> 825.5456
A11: Operating Income | B11: =B6-B10 -> 79 | C11: =C6-C10 -> 221 | D11: =D6-D10 -> 313 | E11: =E6-E10 -> 185 | F11: =F6-F10 -> -42 | G11: =G6-G10 -> 51 | H11: =H6-H10 -> 192 | I11: =I6-I10 -> 1075 | ... S11: =S6-S10 -> 894.04832
A12: Interest Income | B12: -11 | C12: -2 | D12: -24 | E12: -22 | F12: -20 | G12: -36 | H12: -52 | I12: -128 | J12: =J4*-0.0324 -> -149.04 | K12: =K4*-0.0324 -> -148.0032 | L12: =L4*-0.0324 -> -142.5924 | M12: =M4*-0.0324 -> -137.3112 | N12: =N4*-0.0324 -> -126.7488 | O12: =O4*-0.0324 -> -121.4676 | P12: =P4*-0.0324 -> -167.01552 | Q12: =Q4*-0.0324 -> -160.8336 | ... S12: =S4*-0.0324 -> -142.27488
A13: Pretax Income | B13: 54 | C13: -503 | D13: 267 | E13: 173 | F13: -1901 | G13: -1479 | H13: 124 | I13: 937 | J13: =J11+J12 -> 2022.16 | K13: =K11+K12 -> 1916.7328 | L13: =L11+L12 -> 1582.5996 | M13: =M11+M12 -> 1100.1848 | N13: =N11+N12 -> 669.7344 | O13: =O11+O12 -> 641.8288 | P13: =P11+P12 -> 882.50176 | Q13: =Q11+Q12 -> 849.8368 | ... S13: =S11+S12 -> 751.77344
A14: Taxes | B14: 27 | C14: 169 | D14: 56 | E14: 69 | F14: 32 | G14: 162 | H14: 12 | I14: 134 | J14: =J13*0.1199 -> 242.45698 | K14: =K13*0.1199 -> 229.81626 | L14: =L13*0.1199 -> 189.75369 | M14: =M13*0.1199 -> 131.91216 | N14: =N13*0.1199 -> 80.301155 | O14: =O13*0.1199 -> 76.955273 | P14: =P13*0.1199 -> 105.81196 | Q14: =Q13*0.1199 -> 101.89543 | ... S14: =S13*0.1199 -> 90.137635
A15: Net Income | B15: 27 | C15: 120 | D15: 211 | E15: 104 | F15: -1933 | G15: -23 | H15: 112 | I15: 803 | J15: =J13-J14 -> 1779.703 | K15: =K13-K14 -> 1686.9165 | L15: =L13-L14 -> 1392.8459 | M15: =M13-M14 -> 968.27264 | N15: =N13-N14 -> 589.43325 | O15: =O13-O14 -> 564.87353 | P15: =P13-P14 -> 776.6898 | Q15: =Q13-Q14 -> 747.94137 | ... S15: =S13-S14 -> 661.6358
A16: EPS | B16: 0.19 | D16: 1.46 | E16: 0.72 | F16: -13.33 | H16: 0.75 | I16: 5.15 | J16: =IF(J17<>0,J15/J17,"") -> 11.412274 | K16: =IF(K17<>0,K15/K17,"") -> 10.82081 | L16: =IF(L17<>0,L15/L17,"") -> 8.9368844 | M16: =IF(M17<>0,M15/M17,"") -> 6.2138677 | N16: =IF(N17<>0,N15/N17,"") -> 3.7831055 | O16: =IF(O17<>0,O15/O17,"") -> 3.6258721 | P16: =IF(P17<>0,P15/P17,"") -> 4.9862503 | Q16: =IF(Q17<>0,Q15/Q17,"") -> 4.8023835 | ... S16: =IF(S17<>0,S15/S17,"") -> 4.2493437
A17: Shares | B17: 145 | D17: 145 | E17: 145 | F17: 145 | H17: 149 | I17: 156 | J17: =156-(J15*0.55*0.05/913.02) -> 155.9464 | K17: =J17-(K15*0.55*0.05/913.02) -> 155.89559 | L17: =K17-(L15*0.55*0.05/913.02) -> 155.85363 | M17: =L17-(M15*0.55*0.05/913.02) -> 155.82447 | N17: =M17-(N15*0.55*0.05/913.02) -> 155.80672 | O17: =N17-(O15*0.55*0.05/913.02) -> 155.7897 | P17: =O17-(P15*0.55*0.05/913.02) -> 155.76631 | Q17: =P17-(Q15*0.55*0.05/913.02) -> 155.74378 | R17: =Q17-(R15*0.55*0.05/913.02) -> 155.72299 | S17: =R17-(S15*0.55*0.05/913.02) -> 155.70306
A19: Revenue y/y | F19: =F4/B4-1 -> -0.0058651026 | G19: =G4/C4-1 -> 0.080113636 | H19: =H4/D4-1 -> 0.22570366 | I19: =I4/E4-1 -> 0.61247335 | J19: =J4/F4-1 -> 1.7138643 | K19: =K4/G4-1 -> 1.4029458 | L19: =L4/H4-1 -> 0.90684575 | M19: =M4/I4-1 -> 0.40099174 | ... S19: =S4/O4-1 -> 0.17129901
A20: Gross Margin | B20: =IF(B4<>0,B6/B4,"") -> 0.27155425 | C20: =IF(C4<>0,C6/C4,"") -> 0.36136364 | D20: =IF(D4<>0,D6/D4,"") -> 0.38555497 | E20: =IF(E4<>0,E6/E4,"") -> 0.32302772 | F20: =IF(F4<>0,F6/F4,"") -> 0.22536873 | G20: =IF(G4<>0,G6/G4,"") -> 0.26196739 | H20: =IF(H4<>0,H6/H4,"") -> 0.29766031 | I20: =IF(I4<>0,I6/I4,"") -> 0.50942149 | ... S20: =IF(S4<>0,S6/S4,"") -> 0.3916
A22: CFFO | B22: -12 | C22: -130 | D22: -131 | E22: 95 | F22: 26 | G22: 94 | H22: 488 | I22: 1019 | J22: =J4*0.2741 -> 1260.86 | K22: =K4*0.2741 -> 1252.0888 | L22: =L4*0.2741 -> 1206.3141 | M22: =M4*0.2741 -> 1161.6358 | N22: =N4*0.2741 -> 1072.2792 | O22: =O4*0.2741 -> 1027.6009 | P22: =P4*0.2741 -> 1412.9307 | Q22: =Q4*0.2741 -> 1360.6324 | ... S22: =S4*0.2741 -> 1203.6279
A23: CX | B23: 29 | C23: 38 | D23: 67 | E23: 48 | F23: 44 | G23: 45 | H23: 50 | I23: 39 | J23: =J4*0.0173 -> 79.58 | K23: =K4*0.0173 -> 79.0264 | L23: =L4*0.0173 -> 76.1373 | M23: =M4*0.0173 -> 73.3174 | N23: =N4*0.0173 -> 67.6776 | O23: =O4*0.0173 -> 64.8577 | P23: =P4*0.0173 -> 89.17804 | Q23: =Q4*0.0173 -> 85.8772 | ... S23: =S4*0.0173 -> 75.96776
A24: FCF | B24: =B22-B23 -> -41 | C24: =C22-C23 -> -168 | D24: =D22-D23 -> -198 | E24: =E22-E23 -> 47 | F24: =F22-F23 -> -18 | G24: =G22-G23 -> 49 | H24: =H22-H23 -> 438 | I24: =I22-I23 -> 980 | ... S24: =S22-S23 -> 1127.6602
A25: CFFO margin | B25: =IF(B4<>0,B22/B4,"") -> -0.0070381232 | C25: =IF(C4<>0,C22/C4,"") -> -0.073863636 | D25: =IF(D4<>0,D22/D4,"") -> -0.069569835 | E25: =IF(E4<>0,E22/E4,"") -> 0.050639659 | F25: =IF(F4<>0,F22/F4,"") -> 0.015339233 | G25: =IF(G4<>0,G22/G4,"") -> 0.049447659 | H25: =IF(H4<>0,H22/H4,"") -> 0.21143847 | I25: =IF(I4<>0,I22/I4,"") -> 0.3368595 | ... S25: =IF(S4<>0,S22/S4,"") -> 0.2741
A27: Cash | C27: 328 | E27: 804 | F27: 1507 | G27: 1481 | H27: 1442 | I27: 1539
A28: AR | C28: 935 | E28: 904 | F28: 979 | G28: 1068 | H28: 1193 | I28: 1239
A29: Prepaids | C29: 221 | E29: 568 | F29: 391 | G29: 392 | H29: 370 | I29: 357
A30: PP&E | C30: 791 | E30: 579 | F30: 603 | G30: 619 | H30: 630 | I30: 631
A31: Goodwill | C31: 7207 | E31: 6825 | F31: 4997 | G31: 4999 | H31: 4998 | I31: 4995
A32: ONCA | B32: =B33-B27-B28-B29-B30-B31 -> 0 | C32: =C33-C27-C28-C29-C30-C31 -> 4024 | D32: =D33-D27-D28-D29-D30-D31 -> 0 | E32: =E33-E27-E28-E29-E30-E31 -> 4554 | F32: =F33-F27-F28-F29-F30-F31 -> 4483 | G32: =G33-G27-G28-G29-G30-G31 -> 4426 | H32: =H33-H27-H28-H29-H30-H31 -> 4116 | I32: =I33-I27-I28-I29-I30-I31 -> 4237
A33: Assets | C33: 13506 | E33: 14234 | F33: 12960 | G33: 12985 | H33: 12749 | I33: 12998
A35: AP
A36: AL | C36: 424 | E36: 438 | F36: 446 | G36: 425 | H36: 382 | I36: 393
A37: DR
A38: Debt | C38: 0 | F38: 1947 | G38: 1849 | H38: 1351 | I38: 603
A39: ONCL | C39: =2424-C35-C36-C37-C38 -> 2000 | E39: =2233-E35-E36-E37-E38 -> 1795 | F39: =3799-F35-F36-F37-F38 -> 1406 | G39: =3769-G35-G36-G37-G38 -> 1495 | H39: =3368-H35-H36-H37-H38 -> 1635 | I39: =2785-I35-I36-I37-I38 -> 1789
A40: SE | B40: 10939 | C40: 11082 | D40: 12126 | E40: 12001 | F40: 9161 | G40: 9216 | H40: 9381 | I40: 10213
A41: L+SE | B41: =B35+B36+B37+B38+B39+B40 -> 10939 | C41: =C35+C36+C37+C38+C39+C40 -> 13506 | D41: =D35+D36+D37+D38+D39+D40 -> 12126 | E41: =E35+E36+E37+E38+E39+E40 -> 14234 | F41: =F35+F36+F37+F38+F39+F40 -> 12960 | G41: =G35+G36+G37+G38+G39+G40 -> 12985 | H41: =H35+H36+H37+H38+H39+H40 -> 12749 | I41: =I35+I36+I37+I38+I39+I40 -> 12998
A43: ANNUAL SUMMARY ($M)
B44: FY2025 | C44: FY2026 | D44: FY2027 | E44: FY2028
A45: Revenue | B45: =D4+E4+F4+G4 -> 7355 | C45: =H4+I4+J4+K4 -> 14501 | D45: =L4+M4+N4+O4 -> 16300 | E45: =P4+Q4+R4+S4 -> 19092.2
A46: Gross Profit | B46: =D6+E6+F6+G6 -> 2212 | C46: =H6+I6+J6+K6 -> 8187.52 | D46: =L6+M6+N6+O6 -> 7586.8676 | E46: =P6+Q6+R6+S6 -> 7476.5055
A47: Operating Income | B47: =D11+E11+F11+G11 -> 507 | C47: =H11+I11+J11+K11 -> 5502.936 | D47: =L11+M11+N11+O11 -> 4522.4676 | E47: =P11+Q11+R11+S11 -> 3887.1719
A48: Net Income | B48: =D15+E15+F15+G15 -> -1641 | C48: =H15+I15+J15+K15 -> 4381.6196 | D48: =L15+M15+N15+O15 -> 3515.4253 | E48: =P15+Q15+R15+S15 -> 2876.6813
A49: EPS | B49: =D16+E16+F16+G16 -> -11.15 | C49: =H16+I16+J16+K16 -> 28.133084 | D49: =L16+M16+N16+O16 -> 22.55973 | E49: =P16+Q16+R16+S16 -> 18.471584
A50: FCF | B50: =D24+E24+F24+G24 -> -120 | C50: =H24+I24+J24+K24 -> 3772.3424 | D50: =L24+M24+N24+O24 -> 4185.84 | E50: =P24+Q24+R24+S24 -> 4902.877
A52: Revenue Growth | C52: =(H4+I4+J4+K4)/(D4+E4+F4+G4)-1 -> 0.97158396 | D52: =(L4+M4+N4+O4)/(H4+I4+J4+K4)-1 -> 0.12406041 | E52: =(P4+Q4+R4+S4)/(L4+M4+N4+O4)-1 -> 0.17130061
A53: Gross Margin | B53: =IF((D4+E4+F4+G4)<>0,(D6+E6+F6+G6)/(D4+E4+F4+G4),"") -> 0.30074779 | C53: =IF((H4+I4+J4+K4)<>0,(H6+I6+J6+K6)/(H4+I4+J4+K4),"") -> 0.56461761 | D53: =IF((L4+M4+N4+O4)<>0,(L6+M6+N6+O6)/(L4+M4+N4+O4),"") -> 0.465452 | E53: =IF((P4+Q4+R4+S4)<>0,(P6+Q6+R6+S6)/(P4+Q4+R4+S4),"") -> 0.3916
A54: Operating Margin | B54: =IF((D4+E4+F4+G4)<>0,(D11+E11+F11+G11)/(D4+E4+F4+G4),"") -> 0.068932699 | C54: =IF((H4+I4+J4+K4)<>0,(H11+I11+J11+K11)/(H4+I4+J4+K4),"") -> 0.37948666 | D54: =IF((L4+M4+N4+O4)<>0,(L11+M11+N11+O11)/(L4+M4+N4+O4),"") -> 0.277452 | E54: =IF((P4+Q4+R4+S4)<>0,(P11+Q11+R11+S11)/(P4+Q4+R4+S4),"") -> 0.2036
A55: Net Margin | B55: =IF((D4+E4+F4+G4)<>0,(D15+E15+F15+G15)/(D4+E4+F4+G4),"") -> -0.22311353 | C55: =IF((H4+I4+J4+K4)<>0,(H15+I15+J15+K15)/(H4+I4+J4+K4),"") -> 0.30215982 | D55: =IF((L4+M4+N4+O4)<>0,(L15+M15+N15+O15)/(L4+M4+N4+O4),"") -> 0.21567027 | E55: =IF((P4+Q4+R4+S4)<>0,(P15+Q15+R15+S15)/(P4+Q4+R4+S4),"") -> 0.15067312
A56: FCF Margin | B56: =IF((D4+E4+F4+G4)<>0,(D24+E24+F24+G24)/(D4+E4+F4+G4),"") -> -0.016315432 | C56: =IF((H4+I4+J4+K4)<>0,(H24+I24+J24+K24)/(H4+I4+J4+K4),"") -> 0.2601436 | D56: =IF((L4+M4+N4+O4)<>0,(L24+M24+N24+O24)/(L4+M4+N4+O4),"") -> 0.2568 | E56: =IF((P4+Q4+R4+S4)<>0,(P24+Q24+R24+S24)/(P4+Q4+R4+S4),"") -> 0.2568

Sheet Drivers
A1: Sandisk Corp - Revenue Drivers
A2: Input quarterly segment estimates in yellow cells ($Ms). Q4 columns show annual 10-K totals as reference. | Estimates: Mgmt Q2 FY26 call guidance (Jan 29 2026) + H1 actuals + supply-constrained Q4 + seasonality
B3: Q324 | C3: Q424 (FY) | D3: Q125 | E3: Q225 | F3: Q325 | G3: Q425 (FY) | H3: Q126 | I3: Q226 | J3: Q326 | K3: Q426 | L3: Q127 | M3: Q227 | N3: Q327 | O3: Q427 | P3: Q128 | Q3: Q228 | R3: Q328 | S3: Q428 | T3: FY2026E | U3: FY2027E | V3: FY2028E
A4: Cloud | B4: 97 | C4: 325 | D4: 259 | E4: 241 | F4: 197 | G4: 960 | H4: 369 | I4: 605 | J4: 1000 | K4: 1526 | L4: 1323 | M4: 1274 | N4: 1176 | O4: 1127 | P4: 1958 | Q4: 1885.5 | R4: 1740.5 | S4: 1668 | T4: =H4+I4+J4+K4 -> 3500 | U4: =L4+M4+N4+O4 -> 4900 | V4: =P4+Q4+R4+S4 -> 7252
A5: Client | B5: 1035 | C5: 4069 | D5: 1110 | E5: 1037 | F5: 927 | G5: 4127 | H5: 1246 | I5: 1573 | J5: 2300 | K5: 2081 | L5: 2025 | M5: 1950 | N5: 1800 | O5: 1725 | P5: 2126.2 | Q5: 2047.5 | R5: 1890 | S5: 1811.2 | T5: =H5+I5+J5+K5 -> 7200 | U5: =L5+M5+N5+O5 -> 7500 | V5: =P5+Q5+R5+S5 -> 7874.9
A6: Consumer | B6: 573 | C6: 2269 | D6: 514 | E6: 598 | F6: 571 | G6: 2268 | H6: 652 | I6: 907 | J6: 1300 | K6: 961 | L6: 1053 | M6: 1014 | N6: 936 | O6: 897 | P6: 1070.6 | Q6: 1031 | R6: 951.7 | S6: 912 | T6: =H6+I6+J6+K6 -> 3820 | U6: =L6+M6+N6+O6 -> 3900 | V6: =P6+Q6+R6+S6 -> 3965.3
T7: =H7+I7+J7+K7 -> 0 | U7: =L7+M7+N7+O7 -> 0 | V7: =P7+Q7+R7+S7 -> 0
A8: Total Revenue (Driver-Based) | B8: =B4+B5+B6 -> 1705 | C8: =C4+C5+C6 -> 6663 | D8: =D4+D5+D6 -> 1883 | E8: =E4+E5+E6 -> 1876 | F8: =F4+F5+F6 -> 1695 | G8: =G4+G5+G6 -> 7355 | H8: =H4+H5+H6 -> 2267 | I8: =I4+I5+I6 -> 3085 | ... S8: =S4+S5+S6 -> 4391.2 | T8: =H8+I8+J8+K8 -> 14520 | U8: =L8+M8+N8+O8 -> 16300 | V8: =P8+Q8+R8+S8 -> 19092.2
A10: How it works:
A11: 1. Fill in quarterly segment estimates in yellow cells.
A12: 2. Q4 (FY) columns show annual totals from the 10-K as reference.
A13: 3. Green FY columns auto-sum all quarters (actual + estimate)
A14: for the fiscal year. Cell color tells you which is which:
A15: yellow = estimate, plain = reported actual.

Sheet Scenarios
A1: Scenario Manager - Sandisk Corp (SNDK)
A2: Edit yellow cells to override Bear/Base/Bull segment revenue ($M). Changes persist across refresh.
A4: SEGMENT REVENUE BY SCENARIO ($M)
A5: Segment | B5: FY26E Bear | C5: FY26E Base | D5: FY26E Bull | E5: FY27E Bear | F5: FY27E Base | G5: FY27E Bull | H5: FY28E Bear | I5: FY28E Base | J5: FY28E Bull
A6: Cloud | B6: 3400 | C6: 3500 | D6: 3700 | E6: 2500 | F6: 4900 | G6: 6500 | H6: 1800 | I6: 6600 | J6: 9500
A7: Client | B7: 7000 | C7: 7200 | D7: 7400 | E7: 6800 | F7: 7500 | G7: 8500 | H7: 6500 | I7: 7800 | J7: 9500
A8: Consumer | B8: 3700 | C8: 3800 | D8: 3900 | E8: 3500 | F8: 3900 | G8: 4300 | H8: 3300 | I8: 4000 | J8: 4600
A10: TOTAL REVENUE | B10: =B6+B7+B8 -> 14100 | C10: =C6+C7+C8 -> 14500 | D10: =D6+D7+D8 -> 15000 | E10: =E6+E7+E8 -> 12800 | F10: =F6+F7+F8 -> 16300 | G10: =G6+G7+G8 -> 19300 | H10: =H6+H7+H8 -> 11600 | I10: =I6+I7+I8 -> 18400 | J10: =J6+J7+J8 -> 23600
A12: SCENARIO NARRATIVES
A13: Bear thesis: | B13: NAND cycle rolls over late FY26. AI capex pauses; Cloud compresses from $3.4B FY26 to $1.8B FY28. Client -7% cumulative on commodity pricing, Consumer -11%. Op margin re-enters loss territory.
A14: Bull thesis: | B14: AI buildout compounds through FY28. Kioxia JV supply constrains, ASPs stay elevated. Cloud compounds ~75% CAGR to $9.5B by FY28, Client benefits from on-device AI refresh reaching $9.5B, Consumer grows mid-single-digits. Peak margins (25%+) sustained.
A16: How it works:
A17: 1. Yellow cells = your overrides for each scenario's segment revenue
A18: 2. Defaults auto-populated from Drivers tab (Base) and segment volatility (Bear/Bull)

Sheet DCF
A1: DCF Valuation — Sandisk Corp (SNDK)
A3: ASSUMPTIONS
A4: WACC | B4: 0.10311095
A5: Terminal Growth Rate | B5: 0.03
A6: Tax Rate | B6: 0.21
A7: Operating Margin (TTM) | B7: 0.22
A8: CapEx % of Revenue | B8: 0.1
A9: Maintenance CapEx % | B9: 0.075
A10: D&A % of Revenue | B10: 0.1
A11: NWC % of Revenue | B11: 0.13472953
A12: SBC % of Revenue | B12: 0.022846903
A13: Net Dilution Rate (SBC - Buybacks) | B13: 0.0014322713
A15: WACC BUILD
A16: Risk-Free Rate (Rf) | B16: 0.0425
A17: Equity Risk Premium (ERP) | B17: 0.0467
A18: Raw Beta | B18: 2.7281
A19: Blume-Adjusted Beta (Own) | B19: 2.1520667
A20: Peer Blume Beta | B20: 1.7920189
A21: Blended Beta | B21: 1.3
A22: Cost of Equity (Ke = Rf + β×ERP) | B22: 0.10321
A23: Pre-Tax Cost of Debt | B23: 0.1025
A24: After-Tax Cost of Debt | B24: 0.080975
A25: Equity Weight (E/V) | B25: 0.9955454
A26: Debt Weight (D/V) | B26: 0.0044546015
A27: → WACC = (E/V)×Ke + (D/V)×Kd×(1-t) | B27: 0.10311095
A28: Beta Method: | B28: peer blended hardcoded
A29: Sources: | B29: Rf = Yahoo ^TNX (daily) | ERP = Damodaran (monthly)
A31: Revenue Growth Rates:
A32: Year 1 | B32: 0.6262
A33: Year 2 | B33: 0.1226
A34: Year 3 | B34: 0.1713
A35: Year 4 | B35: 0.15
A36: Year 5 | B36: 0.1
A37: Year 6 | B37: 0.06
A38: Year 7 | B38: 0.04
A40: TTM FINANCIALS ($M)
A41: Revenue | B41: 8929
A42: Operating Income | B42: -622
A43: Net Income | B43: -1041
A44: Stock-Based Comp | B44: 204
A45: Share Buybacks | B45: 0
A46: CFFO | B46: 1627
A47: CapEx | B47: 178
A48: Cash | B48: 1539
A49: Debt | B49: 603
A50: Shares Outstanding | B50: 156000000
A52: PROJECTED FREE CASH FLOW ($M)
B53: TTM | C53: Year 1 | D53: Year 2 | E53: Year 3 | F53: Year 4 | G53: Year 5 | H53: Year 6 | I53: Year 7
A54: Revenue Growth | C54: =$B$32 -> 0.6262 | D54: =$B$33 -> 0.1226 | E54: =$B$34 -> 0.1713 | F54: =$B$35 -> 0.15 | G54: =$B$36 -> 0.1 | H54: =$B$37 -> 0.06 | I54: =$B$38 -> 0.04
A55: Revenue | B55: 8929 | C55: =B55*(1+C54) -> 14520.34 | D55: =C55*(1+D54) -> 16300.533 | E55: =D55*(1+E54) -> 19092.815 | F55: =E55*(1+F54) -> 21956.737 | G55: =F55*(1+G54) -> 24152.411 | H55: =G55*(1+H54) -> 25601.555 | I55: =H55*(1+I54) -> 26625.618
A56: Operating Margin | B56: -0.069660656 | C56: 0.22 | D56: 0.22 | E56: 0.22 | F56: 0.22 | G56: 0.22 | H56: 0.22 | I56: 0.22
A57: Operating Income | B57: -622 | C57: =C55*C56 -> 3194.4748 | D57: =D55*D56 -> 3586.1174 | E57: =E55*E56 -> 4200.4193 | F57: =F55*F56 -> 4830.4822 | G57: =G55*G56 -> 5313.5304 | H57: =H55*H56 -> 5632.3422 | I57: =I55*I56 -> 5857.6359
A58: NOPAT | C58: =C57*(1-$B$6) -> 2523.6351 | D58: =D57*(1-$B$6) -> 2833.0327 | E58: =E57*(1-$B$6) -> 3318.3312 | F58: =F57*(1-$B$6) -> 3816.0809 | G58: =G57*(1-$B$6) -> 4197.689 | H58: =H57*(1-$B$6) -> 4449.5503 | I58: =I57*(1-$B$6) -> 4627.5323
A59: D&A | C59: =C55*$B$10 -> 1452.034 | D59: =D55*$B$10 -> 1630.0533 | E59: =E55*$B$10 -> 1909.2815 | F59: =F55*$B$10 -> 2195.6737 | G59: =G55*$B$10 -> 2415.2411 | H59: =H55*$B$10 -> 2560.1555 | I59: =I55*$B$10 -> 2662.5618
A60: CapEx | C60: =C55*C61 -> 1452.034 | D60: =D55*D61 -> 1561.5911 | E60: =E55*E61 -> 1750.8111 | F60: =F55*F61 -> 1921.2145 | G60: =G55*G61 -> 2011.8958 | H60: =H55*H61 -> 2027.6432 | I60: =I55*I61 -> 1996.9213
A61: CapEx % | C61: 0.1 | D61: 0.0958 | E61: 0.0917 | F61: 0.0875 | G61: 0.0833 | H61: 0.0792 | I61: 0.075
A62: Change in NWC | C62: =$B$11*(C55-B55) -> 753.3186 | D62: =$B$11*(D55-C55) -> 239.84466 | E62: =$B$11*(E55-D55) -> 376.20277 | F62: =$B$11*(F55-E55) -> 385.8549 | G62: =$B$11*(G55-F55) -> 295.82209 | H62: =$B$11*(H55-G55) -> 195.24258 | I62: =$B$11*(I55-H55) -> 137.97142
A63: Stock-Based Comp | C63: =C55*$B$12 -> 331.7448 | D63: =D55*$B$12 -> 372.41671 | E63: =E55*$B$12 -> 436.2117 | F63: =F55*$B$12 -> 501.64345 | G63: =G55*$B$12 -> 551.80779 | H63: =H55*$B$12 -> 584.91626 | I63: =I55*$B$12 -> 608.31291
A64: Free Cash Flow | C64: =C58+C59-C60-C62-C63 -> 1438.5717 | D64: =D58+D59-D60-D62-D63 -> 2289.2336 | E64: =E58+E59-E60-E62-E63 -> 2664.3871 | F64: =F58+F59-F60-F62-F63 -> 3203.0418 | G64: =G58+G59-G60-G62-G63 -> 3753.4044 | H64: =H58+H59-H60-H62-H63 -> 4201.9038 | I64: =I58+I59-I60-I62-I63 -> 4546.8884
A65: FCF Margin | C65: =IF(C55<>0,C64/C55,0) -> 0.099072864 | D65: =IF(D55<>0,D64/D55,0) -> 0.14043918 | E65: =IF(E55<>0,E64/E55,0) -> 0.1395492 | F65: =IF(F55<>0,F64/F55,0) -> 0.14587968 | G65: =IF(G55<>0,G64/G55,0) -> 0.15540496 | H65: =IF(H55<>0,H64/H55,0) -> 0.1641269 | I65: =IF(I55<>0,I64/I55,0) -> 0.17077119
A67: DISCOUNTED CASH FLOWS ($M)
A68: PV of FCF | C68: =C64/(1+$B$4)^1 -> 1304.1042 | D68: =D64/(1+$B$4)^2 -> 1881.2725 | E68: =E64/(1+$B$4)^3 -> 1984.905 | F68: =F64/(1+$B$4)^4 -> 2163.1459 | G68: =G64/(1+$B$4)^5 -> 2297.8907 | H68: =H64/(1+$B$4)^6 -> 2332.0128 | I68: =I64/(1+$B$4)^7 -> 2287.5991
A69: Terminal Value | B69: =I64*(1+$B$5)/($B$4-$B$5) -> 64057.367
A70: PV of Terminal Value | B70: =B69/(1+$B$4)^7 -> 32228.101
A72: VALUATION SUMMARY
A73: Sum of PV(FCFs) | B73: =SUM(C68:I68) -> 14250.93
A74: PV of Terminal Value | B74: =B70 -> 32228.101
A75: Enterprise Value | B75: =B73+B74 -> 46479.031
A76: Terminal Value % of EV | B76: =IF(B75<>0,B74/B75,0) -> 0.69339011
A77: Less: Debt | B77: =-B49 -> -603
A78: Plus: Cash | B78: =B48 -> 1539
A79: Equity Value | B79: =B75+B77+B78 -> 47415.031
A80: Current Shares (M) | B80: =B50/1000000 -> 156
A81: Diluted Shares (M, End of Projection) | B81: =B80*(1+0.0014)^7 -> 157.53524
A82: Implied Share Price | B82: =IF(B81<>0,B79/B81,0) -> 300.98048
A84: TERMINAL VALUE CROSS-CHECK
A85: Perpetuity Growth Method | B85: =B69 -> 64057.367
A86: Exit Multiple Method (38x EBITDA) | B86: 324432
A87: Note: Compare both methods. Large gaps suggest fragile assumptions.
A88: Current Market Price | B88: 913.02
A89: Upside / Downside | B89: =B82/B88-1 -> -0.67034623
A91: SCENARIO ANALYSIS
A92: Three scenarios based on different growth and margin assumptions
B93: Bear | C93: Base | D93: Bull
A94: Implied Share Price | B94: 157.30368 | C94: 312.78935 | D94: 456.37126
A95: vs Current Price | B95: -0.82771059 | C95: -0.65741238 | D95: -0.50015196
A96: Year 1 Growth | B96: -0.1191 | C96: 0.6262 | D96: 1.3715
A97: Year 7 Growth | B97: 0.03 | C97: 0.04 | D97: 0.03
A98: Year 1 Op Margin | B98: 0.11 | C98: 0.22 | D98: 0.27
A99: Year 7 Op Margin | B99: 0.2185 | C99: 0.22 | D99: 0.219
A100: Dilution (Annual SBC) | B100: 0.0014322713 | C100: 0.0014322713 | D100: 0.0014322713
A102: MARGIN REVERSION (stress case — base growth, mid-cycle margins)
A103: Stress Implied Share Price | B103: 229.19132
A104: vs Base Case ($312.79) | B104: -0.26726623
A105: vs Current Market ($913.02) | B105: -0.74897448
A106: Year 1 → Year N Op Margin | B106: 22.0% → 15.0%
A107: Holds driver-based revenue growth constant. Fades op margin linearly from TTM to margin target − 5pp. Tests what happens if today's peak margins normalize to mid-cycle without any change in revenue trajectory.
A110: SENSITIVITY: WACC × Terminal Growth → Implied Price
A111: Each cell shows the implied share price under that WACC / Terminal Growth combo
A112: WACC ↓ / TGR → | B112: 0.015 | C112: 0.02 | D112: 0.025 | E112: 0.03 | F112: 0.035
...

Sheet Reverse DCF
A1: Reverse DCF — Sandisk Corp (SNDK)
A2: What annual FCF growth rate is the market pricing in at today's stock price?
A4: RESULT
A5: Implied Annual FCF Growth | B5: 0.50196533
A6: Current Stock Price | B6: 913.02
A8: HISTORICAL REVENUE GROWTH (CAGR)
A9: 1yr Avg Revenue Growth | B9: 0.23601883
A10: ⚠ Market implies 50% growth vs 24% historical — aggressive pricing
A12: The market expects very high growth (50%/yr). High expectations = high risk if growth slows.
A14: WHAT MUST BE TRUE FOR $913 TO BE FAIR VALUE
A15: Market price requires AT LEAST ONE of these (not all three) — each holds other base-case operational assumptions constant.
A16: Required TTM Revenue (starting point) | B16: 31489.549 | C16: vs base $8,929M (Δ +253%)
A17: Required Operating Margin (held constant) | B17: 0.67209473 | C17: vs base 22.0% (Δ +45.2pp) → implied FCF margin 50.8%
A18: Required Terminal Growth Rate | B18: 0.086774925 | C18: vs base 3.0% (Δ +5.7pp)
A20: ASSUMPTIONS USED | C20: (linked to DCF tab)
A21: WACC | B21: =DCF!B4 -> 0.10311095
A22: Terminal Growth Rate | B22: =DCF!B5 -> 0.03
A23: Tax Rate | B23: =DCF!B6 -> 0.21
A24: Operating Margin | B24: =DCF!B7 -> 0.22
A25: CapEx % of Revenue | B25: =DCF!B8 -> 0.1
A26: D&A % of Revenue | B26: =DCF!B10 -> 0.1
A28: SENSITIVITY TABLE
A29: Implied FCF Growth Rate for different WACC / Terminal Growth combos
A30: WACC ↓ / TGR → | B30: 0.01 | C30: 0.015 | D30: 0.02 | E30: 0.025 | F30: 0.03 | G30: 0.035 | H30: 0.04
A31: 0.0731 | B31: 0.4293335 | C31: 0.4116333 | D31: 0.3925293 | E31: 0.37171631 | F31: 0.34888916 | G31: 0.32355957 | H31: 0.29511719
A32: 0.0831 | B32: 0.47474365 | C32: 0.45924072 | D32: 0.44257812 | E32: 0.42475586 | F32: 0.40546875 | G32: 0.38447266 | H32: 0.36140137
A33: 0.0931 | B33: 0.51697998 | C33: 0.50306396 | D33: 0.48835449 | E33: 0.47266846 | F33: 0.45588379 | G33: 0.43781738 | H33: 0.41834717
A34: 0.1031 | B34: 0.55671387 | C34: 0.54414063 | D34: 0.53083496 | E34: 0.51679688 | F34: 0.5019043 | G34: 0.48606567 | H34: 0.46912842
A35: 0.1131 | B35: 0.59449463 | C35: 0.58295898 | D35: 0.57081299 | E35: 0.55811768 | F35: 0.54468994 | G35: 0.53052979 | H35: 0.5154541
A36: 0.1231 | B36: 0.63062744 | C36: 0.61994629 | D36: 0.60877686 | E36: 0.59711914 | F36: 0.58491211 | G36: 0.57203369 | H36: 0.55854492
A37: 0.1331 | B37: 0.66541748 | C37: 0.65546875 | D37: 0.64515381 | E37: 0.63435059 | F37: 0.62312012 | G37: 0.61134033 | H37: 0.59901123
A40: GROWTH × MARGIN GRID (Implied Price)
A41: Each cell = implied share price for that (revenue CAGR, op margin) combo. Find the cell closest to current price; that pair is what the market is pricing.
A42: Op Margin ↓ / Rev CAGR → | B42: 0.40196533 | C42: 0.45196533 | D42: 0.50196533 | E42: 0.55196533 | F42: 0.60196533
A43: 0.12 | B43: 187.01048 | C43: 211.32746 | D43: 236.52079 | E43: 261.96494 | F43: 286.84041
A44: 0.17 | B44: 401.63863 | C44: 481.62148 | D44: 574.78223 | E44: 682.71194 | F44: 807.11833
A45: 0.22 | B45: 616.26678 | C45: 751.91549 | D45: 913.04368 | E45: 1103.4589 | F45: 1327.3962
A46: 0.27 | B46: 830.89492 | C46: 1022.2095 | D46: 1251.3051 | E46: 1524.2059 | F46: 1847.6741
A47: 0.32 | B47: 1045.5231 | C47: 1292.5035 | D47: 1589.5666 | E47: 1944.953 | F47: 2367.9521
A49: At current price $913.02, the market is pricing in approximately 50% revenue CAGR AT 22% operating margin. Move along either axis to see the trade-off.
A52: MARKET-IMPLIED WACC
A53: Holding our growth and margin base case, what discount rate does today's price imply? If this is materially below our computed WACC, the market is pricing less risk than our beta methodology assumes.
A54: Our Computed WACC | B54: 0.10311095
A55: Market-Implied WACC | B55: 0.052067566
A56: Gap (Ours − Market) | B56: 0.051043386
A57: We discount at 5.1pp HIGHER than the market. Closing this gap (lower beta or longer return horizon) would push our DCF toward sell-side targets.

Sheet Monte Carlo
A1: Monte Carlo DCF Simulation - Sandisk Corp (SNDK)
A3: METHODOLOGY
A4: 1,000 iterations (1,000 valid)
A5: Operating variables: correlated blend between Bear/Base/Bull scenarios
A6: WACC: Normal(10.3%, 1.5% std) | TGR: Triangular(1.5%, 3.0%, 4.5%)
A7: Revenue exec shock: ±15% σ (multiplicative, ±2σ clipped) | Margin exec shock: ±3.0pp σ (additive, ±2σ clipped)
A8: Seed: 42 (deterministic — same inputs produce same output)
A10: SUMMARY STATISTICS
A11: Mean Implied Price | B11: 304.36905
A12: Median Implied Price (50th pctl) | B12: 287.10927
A13: Standard Deviation | B13: 116.58176
A15: PERCENTILE TABLE
A16: Percentile | B16: Implied Price | C16: vs Current
A17: 5th | B17: 158.15102 | C17: -0.82678252
A18: 25th | B18: 225.26146 | C18: -0.75327872
A19: 50th | B19: 287.10927 | C19: -0.68553891
A20: 75th | B20: 357.07148 | C20: -0.60891165
A21: 95th | B21: 510.32069 | C21: -0.44106297
A23: PROBABILITY ANALYSIS
A24: Current Share Price | B24: 913.02
A25: P(Undervalued) | B25: 0.002 | C25: Majority of scenarios imply downside
A27: SCENARIO ANCHORS
A28: Bear Implied | B28: 157.30368
A29: Base Implied | B29: 312.78935
A30: Bull Implied | B30: 456.37126
A32: PRICE DISTRIBUTION
A33: $81-$142 | B33: ███ | C33: (20)
A34: $142-$203 | B34: █████████████████████████ | C34: (154)
A35: $203-$263 | B35: ███████████████████████████████████████ | C35: (235)
A36: $263-$324 | B36: ████████████████████████████████████████ | C36: (239)
A37: $324-$385 | B37: ██████████████████████████ | C37: (160)
A38: $385-$446 | B38: █████████████ | C38: (82)
A39: $446-$506 | B39: █████████ | C39: (54)
A40: $506-$567 | B40: █████ | C40: (30)
A41: $567-$628 | B41: █ | C41: (11)
A42: $628-$688 | B42: █ | C42: (7)
A43: $688-$749 | C43: (3)
A44: $749-$810 | C44: (1)
A45: $810-$871 | C45: (2)
A46: $871-$931 | C46: (0)
A47: $931-$992 | C47: (0)
A48: $992-$1053 | C48: (1)
A49: $1053-$1113 | C49: (0)
A50: $1113-$1174 | C50: (0)
A51: $1174-$1235 | C51: (0)
A52: $1235-$1296 | C52: (1)

Sheet Comps
A1: Comparable Company Analysis
A3: Ticker | B3: Company | C3: Market Cap ($B) | D3: Price | E3: Trailing P/E | F3: Forward P/E | G3: EV/EBITDA | H3: P/S | I3: EV/Rev | J3: P/B | K3: PEG | L3: Rev Growth | M3: Gross Margin | N3: Op Margin | O3: Net Margin | P3: ROE | Q3: Div Yield
A4: WDC | B4: Western Digital Corporation | C4: 127.90794 | D4: 374.11 | E4: 35.36011 | F4: 26.668386 | G4: 38.078 | I4: 11.909 | J4: 17.887161 | K4: 0.75 | L4: 0.252 | M4: 0.42723998 | N4: 0.31919 | O4: 0.35644 | P4: 0.41126 | Q4: 0.13
A5: STX | B5: Seagate Technology Holdings PLC | C5: 120.9177 | D5: 539.75 | E5: 61.756294 | F5: 26.32521 | G5: 42.589 | I5: 12.076 | J5: 256.53516 | K5: 0.83 | L5: 0.215 | M5: 0.38775003 | N5: 0.29947 | O5: 0.19586 | Q5: 0.54
A6: MU | B6: Micron Technology, Inc. | C6: 505.69852 | D6: 448.42 | E6: 21.141916 | F6: 4.436568 | G6: 13.638 | I6: 8.636 | J6: 6.9807124 | K6: 0.26 | L6: 1.963 | M6: 0.58437 | N6: 0.67624 | O6: 0.41486 | P6: 0.39823002 | Q6: 0.13
A7: Median | E7: 35.36011 | F7: 26.32521 | G7: 38.078 | I7: 11.909 | J7: 17.887161 | K7: 0.75 | L7: 0.252 | M7: 0.42723998 | N7: 0.31919 | O7: 0.35644 | P7: 0.40474501 | Q7: 0.13

Sheet Multiples
A1: Multiple-Based Valuation — Sandisk Corp (SNDK)
A2: Peers: WDC, STX, MU
A4: FORWARD METRICS ($M)
A5: NTM EPS (Trailing Margin) | B5: -7.14
A6: Normalized EPS (Mid-Cycle Avg Margin) | B6: -4.83
A7: NTM EBITDA (Projected OpInc + D&A) | B7: -319.95
A8: NTM EBIT (Operating Income) | B8: -466.95
A9: NTM Revenue (Projected) | B9: 11534.19
A10: TTM Free Cash Flow | B10: 1449
A11: FCF Yield (TTM FCF / EV) | B11: 0.01
A12: Shares Outstanding (M) | B12: 156
A13: Cash | B13: 1539
A14: Debt | B14: 603
A15: Book Value (Stockholders' Equity) | B15: 10213
A16: Book Value Per Share | B16: 65.47
... A20: Days Inventory Outstanding | B20: 123.53
A22: DUPONT ROE DECOMPOSITION
A23: Net Profit Margin (NI / Revenue) | B23: -0.1166
A24: Asset Turnover (Revenue / Assets) | B24: 0.687
A25: Equity Multiplier (Assets / Equity) | B25: 1.2727
A26: Return on Equity (ROE) | B26: -0.1019
A28: GEOGRAPHIC REVENUE SPLIT | B28: (Source: 10-K filing)
A29: Asia | B29: 0.606 | C29: ██████████████████
A30: Americas | B30: 0.22 | C30: ██████
A31: EMEA | B31: 0.174 | C31: █████
A33: CUSTOMER CONCENTRATION | B33: (Source: 10-K filing)
A34: Status: CONCENTRATED
A35: 15% of total revenue
A37: For 2025 and 2024, no customer accounted for more than 10% of our net revenue. For 2023, one customer accounted for 15% of our net revenue. For 2025 and 2024 no single customer accounted for more than 10% of the Company’s net revenue.
A39: VALUATION BY MULTIPLES
A40: Method | B40: Low Multiple | C40: Mid Multiple | D40: High Multiple | E40: Low Price | F40: Mid Price | G40: High Price
A41: Forward P/E | B41: N/A
A42: EV/EBITDA | B42: N/A
A43: EV/EBIT | B43: N/A
A44: EV/Revenue | B44: 10.12265 | C44: 11.909 | D44: 13.69535 | E44: =IF($B$12<>0,($B$9*B44-$B$14+$B$13)/$B$12,0) -> 754.43954 | F44: =IF($B$12<>0,($B$9*C44-$B$14+$B$13)/$B$12,0) -> 886.51711 | G44: =IF($B$12<>0,($B$9*D44-$B$14+$B$13)/$B$12,0) -> 1018.5947
A46: Current Market Price | B46: 913.02
A47: Premium / Discount to Mid
A48: EV/Revenue | B48: =IF(B46<>0,F44/B46-1,0) -> -0.029027724
A50: VALUATION RANGE SUMMARY
A51: Overall Low | B51: =MIN(E44) -> 754.43954
A52: Overall Mid (Average) | B52: =AVERAGE(F44) -> 886.51711
A53: Overall High | B53: =MAX(G44) -> 1018.5947
A55: METHOD RELEVANCE NOTES
A56: CYCLE-ADJUSTMENT NOTE: Peer multiples (10-14x EV/Rev, ~38x EV/EBITDA) reflect peer peak-cycle pricing. Applying them to SNDK's peak revenue double-counts cycle risk. See DCF for cycle-adjusted view.
A57: Preferred Method | B57: EV/Revenue
A58: CAUTION: Forward EPS is negative ($-7.14). P/E valuation is not applicable. Use EV-based methods.
A59: CAUTION: Negative EBITDA makes this multiple unreliable. Weight EV/Revenue more heavily.
